check_sl_delay/__init__.py
check_sl_delay/check_sl_delay.py
check_sl_delay-0.1.3.dist-info/LICENSE
check_sl_delay-0.1.3.dist-info/METADATA
check_sl_delay-0.1.3.dist-info/WHEEL
check_sl_delay-0.1.3.dist-info/entry_points.txt
check_sl_delay-0.1.3.dist-info/top_level.txt
check_sl_delay-0.1.3.dist-info/RECORD
