Metadata-Version: 2.1
Name: check-sl-delay
Version: 0.1.3
Summary: Nagios plugin to check SL delays for a given site
Home-page: UNKNOWN
Author: Johan Thorén
Author-email: johan@thoren.xyz
License: ISC license
Keywords: check_sl_delay
Platform: UNKNOWN
Classifier: Development Status :: 5 - Production/Stable
Classifier: Intended Audience :: System Administrators
Classifier: License :: OSI Approved :: ISC License (ISCL)
Classifier: Natural Language :: English
Classifier: Programming Language :: Python :: 3
Classifier: Programming Language :: Python :: 3.6
Classifier: Programming Language :: Python :: 3.7
Classifier: Programming Language :: Python :: 3.8
Requires-Python: >=3.6
Requires-Dist: requests (>=2.23)
Requires-Dist: Click (>=7.1)
Requires-Dist: func-timeout (>=4.3)
